{"version": 0.6, "generator": "Overpass API 0.7.62.1 084b4234", "osm3s": {"timestamp_osm_base": "2024-04-10T04:11:52Z", "copyright": "The data included in this document is from www.openstreetmap.org. The data is made available under ODbL."}, "elements": [{"type": "node", "id": 356842742, "lat": 30.3140915, "lon": -97.7422299, "tags": {"amenity": "place_of_worship", "denomination": "baptist", "ele": "200", "gnis:county_id": "453", "gnis:created": "12/09/2003", "gnis:feature_id": "2024532", "gnis:state_id": "48", "name": "Saint Olives Missionary Baptist Church", "religion": "christian"}}, {"type": "node", "id": 530778738, "lat": 30.3158003, "lon": -97.7416401, "tags": {"amenity": "cafe", "name": "Upper Crust Bakery", "wheelchair": "limited"}}, {"type": "node", "id": 531864811, "lat": 30.3145527, "lon": -97.7404766, "tags": {"addr:city": "Austin", "addr:housenumber": "1207", "addr:postcode": "78756", "addr:state": "TX", "addr:street": "West 45th Street", "amenity": "place_of_worship", "denomination": "lutheran", "name": "Trinity Lutheran Church", "phone": "+1-512-453-3835", "religion": "christian", "website": "https://www.trinityaustin.com/", "wheelchair": "limited"}}, {"type": "node", "id": 3852094467, "lat": 30.315165, "lon": -97.741972}, {"type": "node", "id": 3852094503, "lat": 30.3152, "lon": -97.742042}, {"type": "node", "id": 3852094565, "lat": 30.315272, "lon": -97.7419}, {"type": "node", "id": 3852094592, "lat": 30.315307, "lon": -97.74197}, {"type": "way", "id": 382005960, "nodes": [3852094565, 3852094467, 3852094503, 3852094592, 3852094565], "tags": {"addr:housenumber": "4416", "addr:street": "Burnet Road", "amenity": "cafe", "building": "yes", "height": "5.0", "name": "Stinson's"}}]}